calpit/__init__.py
calpit/_version.py
calpit/datasets.py
calpit/diagnostics_and_calibration.py
calpit/example_benchmarks.py
calpit/metrics.py
calpit/py.typed
calpit/utils.py
calpit/nn/__init__.py
calpit/nn/ispline_nn.py
calpit/nn/models.py
calpit/nn/utils.py
calpit/nn/umnn/MonotonicNN.py
calpit/nn/umnn/NeuralIntegral.py
calpit/nn/umnn/ParallelNeuralIntegral.py
calpit/nn/umnn/__init__.py
calpit-0.1.2.dist-info/LICENSE
calpit-0.1.2.dist-info/METADATA
calpit-0.1.2.dist-info/WHEEL
calpit-0.1.2.dist-info/top_level.txt
calpit-0.1.2.dist-info/RECORD
